brickflow/__init__.py
brickflow/bundles/__init__.py
brickflow/bundles/model.py
brickflow/cli/__init__.py
brickflow/cli/bundles.py
brickflow/cli/commands.py
brickflow/cli/configure.py
brickflow/cli/constants.py
brickflow/cli/entrypoint.template
brickflow/cli/gitignore_template.txt
brickflow/cli/projects.py
brickflow/codegen/__init__.py
brickflow/codegen/databricks_bundle.py
brickflow/context/__init__.py
brickflow/context/context.py
brickflow/engine/__init__.py
brickflow/engine/compute.py
brickflow/engine/hooks.py
brickflow/engine/project.py
brickflow/engine/task.py
brickflow/engine/utils.py
brickflow/engine/workflow.py
brickflow/hints/__init__.py
brickflow/hints/hint.py
brickflow/hints/py.typed
brickflow/resolver/__init__.py
brickflow_plugins/__init__.py
brickflow_plugins/airflow/__init__.py
brickflow_plugins/airflow/brickflow_task_plugin.py
brickflow_plugins/airflow/context/__init__.py
brickflow_plugins/airflow/cronhelper.py
brickflow_plugins/airflow/operators/__init__.py
brickflow_plugins/airflow/operators/external_tasks.py
brickflow_plugins/airflow/operators/external_tasks_tableau.py
brickflow_plugins/airflow/operators/native_operators.py
brickflow_plugins/airflow/vendor/__init__.py
brickflow_plugins/airflow/vendor/context.py
brickflow_plugins/airflow/vendor/timetable.py
brickflow_plugins/airflow/vendor/timezone.py
brickflow_plugins/databricks/__init__.py
brickflow_plugins/databricks/box_operator.py
brickflow_plugins/databricks/run_job.py
brickflow_plugins/databricks/sla_sensor.py
brickflow_plugins/databricks/uc_to_snowflake_operator.py
brickflow_plugins/databricks/workflow_dependency_sensor.py
brickflow_plugins/secrets/__init__.py
brickflows-1.4.1.dist-info/LICENSE
brickflows-1.4.1.dist-info/METADATA
brickflows-1.4.1.dist-info/WHEEL
brickflows-1.4.1.dist-info/entry_points.txt
brickflows-1.4.1.dist-info/RECORD
