Metadata-Version: 2.3
Name: brickflows
Version: 1.4.1
Summary: Deploy scalable workflows to databricks using python
License: Apache-2.0
Author: Ashok Singamaneni, Sriharsha Tikkireddy
Requires-Python: >=3.9,<3.13
Classifier: License :: OSI Approved :: Apache Software License
Classifier: Programming Language :: Python :: 3
Classifier: Programming Language :: Python :: 3.9
Classifier: Programming Language :: Python :: 3.10
Classifier: Programming Language :: Python :: 3.11
Classifier: Programming Language :: Python :: 3.12
Requires-Dist: Jinja2 (>=3.1.5)
Requires-Dist: click (>=8.1.3,<9.0.0)
Requires-Dist: databricks-sdk (>=0.1.8,<1.0.0)
Requires-Dist: networkx (==3.1)
Requires-Dist: pendulum (==3.1.0)
Requires-Dist: pluggy (>=1.0.0,<2.0.0)
Requires-Dist: pydantic (>=2.0.0,<3.0.0)
Requires-Dist: python-decouple (==3.8)
Requires-Dist: pyyaml (>=6.0,<7.0)
Requires-Dist: requests (>=2.28.2,<3.0.0)
Project-URL: Homepage, https://github.com/Nike-Inc/brickflow
Project-URL: Repository, https://github.com/Nike-Inc/brickflow
